uchkin_diploma/NeuralNetwork.py
uchkin_diploma/__init__.py
uchkin_diploma/saved_who.npy
uchkin_diploma/saved_wih.npy
uchkin_diploma-1.0.3.dist-info/LICENSE
uchkin_diploma-1.0.3.dist-info/METADATA
uchkin_diploma-1.0.3.dist-info/WHEEL
uchkin_diploma-1.0.3.dist-info/top_level.txt
uchkin_diploma-1.0.3.dist-info/RECORD
